oats/__init__.py
oats/_version.py
oats/core.py
pyclstr/__init__.py
pyclstr/_version.py
pyclstr/core.py
simplecluster/__init__.py
simplecluster/_version.py
simplecluster/core.py
pyclstr-0.0.2.post0.dev1.dist-info/LICENSE.md
pyclstr-0.0.2.post0.dev1.dist-info/METADATA
pyclstr-0.0.2.post0.dev1.dist-info/WHEEL
pyclstr-0.0.2.post0.dev1.dist-info/top_level.txt
pyclstr-0.0.2.post0.dev1.dist-info/zip-safe
pyclstr-0.0.2.post0.dev1.dist-info/RECORD
