Metadata-Version: 2.1
Name: pyclstr
Version: 0.0.2.post0.dev1
Summary: Simple clustering algorithms
Home-page: https://www.lockhartlab.org/
Author: Chris Lockhart
Author-email: clockha2@gmu.edu
License-File: LICENSE.md
Requires-Dist: numpy
